song_schema/__init__.py
song_schema/clips.py
song_schema/devices.py
song_schema/metadata.py
song_schema/mixing.py
song_schema/song.py
song_schema/structure.py
song_schema/tracks.py
song_schema/validate.py
song_schema-0.1.0.dist-info/METADATA
song_schema-0.1.0.dist-info/WHEEL
song_schema-0.1.0.dist-info/RECORD
