Metadata-Version: 2.3
Name: song-schema
Version: 0.1.0
Summary: Pydantic models for defining Ableton Live song configurations
Author: ldraney
Requires-Python: >=3.11
Classifier: Programming Language :: Python :: 3
Classifier: Programming Language :: Python :: 3.11
Classifier: Programming Language :: Python :: 3.12
Classifier: Programming Language :: Python :: 3.13
Requires-Dist: pydantic (>=2.12.5,<3.0.0)
